langstream/__init__.py
langstream/contrib/__init__.py
langstream/contrib/llms/__init__.py
langstream/contrib/llms/gpt4all_stream.py
langstream/contrib/llms/lite_llm.py
langstream/contrib/llms/open_ai.py
langstream/core/__init__.py
langstream/core/stream.py
langstream/utils/__init__.py
langstream/utils/_typing.py
langstream/utils/async_generator.py
langstream/utils/stream.py
langstream-0.3.1.dist-info/LICENSE
langstream-0.3.1.dist-info/METADATA
langstream-0.3.1.dist-info/WHEEL
langstream-0.3.1.dist-info/RECORD
