Metadata-Version: 2.1
Name: langstream
Version: 0.3.1
Summary: Build robust LLM applications with true composability
Home-page: https://github.com/rogeriochaves/langstream
License: MIT
Author: Rogerio Chaves
Author-email: rogeriocfj@gmail.com
Requires-Python: >=3.9,<4.0
Classifier: Development Status :: 4 - Beta
Classifier: Intended Audience :: Developers
Classifier: License :: OSI Approved :: MIT License
Classifier: Operating System :: OS Independent
Classifier: Programming Language :: Python :: 3
Classifier: Programming Language :: Python :: 3.9
Classifier: Programming Language :: Python :: 3.10
Classifier: Programming Language :: Python :: 3.11
Classifier: Programming Language :: Python :: 3.12
Classifier: Topic :: Software Development :: Libraries :: Python Modules
Provides-Extra: gpt4all
Provides-Extra: litellm
Provides-Extra: openai
Requires-Dist: asyncstdlib (>=3.10.8,<4.0.0)
Requires-Dist: colorama (>=0.4.6,<0.5.0)
Requires-Dist: gpt4all (>=2.0.2) ; extra == "gpt4all"
Requires-Dist: litellm (>=1.16.12) ; extra == "litellm"
Requires-Dist: openai (>=1.6.1) ; extra == "openai"
Requires-Dist: retry
Project-URL: Documentation, https://rogeriochaves.github.io/langstream/
Project-URL: Issue Tracker, https://github.com/rogeriochaves/langstream/issues
Project-URL: Source Code, https://github.com/rogeriochaves/langstream
